atg/__init__.py
atg/main.py
ATG_Engine_Test-1.0.0.dist-info/LICENSE
ATG_Engine_Test-1.0.0.dist-info/METADATA
ATG_Engine_Test-1.0.0.dist-info/WHEEL
ATG_Engine_Test-1.0.0.dist-info/top_level.txt
ATG_Engine_Test-1.0.0.dist-info/zip-safe
ATG_Engine_Test-1.0.0.dist-info/RECORD
