Metadata-Version: 2.1
Name: ATG-Engine-Test
Version: 1.0.0
Summary: An advanced module for making advanced text based games.
Home-page: UNKNOWN
Author: danrandomprogrammer
Author-email: devpsingh2020@gmail.com
License: GNU General Public License v3 (GPLv3)
Platform: UNKNOWN
Classifier: Programming Language :: Python :: 3
Classifier: License :: OSI Approved :: GNU General Public License v3 (GPLv3)
Classifier: Operating System :: OS Independent
Requires-Python: >=3.5
